[
    {
        "id": "TEAM-001",
        "name": "DarkZero",
        "teamLogoUrl": "https://raw.githubusercontent.com/StefDB6/Webontwikkeling_2025/refs/heads/main/Images/DarkZero_Logo.png",
        "foundedYear": 2018,
        "manager": "Zach Matula",
        "region": "North America"
    },
    {
        "id": "TEAM-002",
        "name": "Faze Clan",
        "labelLogoUrl": "https://raw.githubusercontent.com/StefDB6/Webontwikkeling_2025/refs/heads/main/Images/Faze_Clan_Logo.png",
        "foundedYear": 2011,
        "manager": "Leando Portela",
        "region": "South America"
    },
    {
        "id": "TEAM-003",
        "name": "BDS",
        "teamLogoUrl": "https://raw.githubusercontent.com/StefDB6/Webontwikkeling_2025/refs/heads/main/Images/BDS_Logo.png",
        "foundedYear": 2019,
        "manager": "Alexia Chapus",
        "region": "Europe"
    },
    {
        "id": "TEAM-004",
        "name": "Liquid",
        "teamLogoUrl": "https://raw.githubusercontent.com/StefDB6/Webontwikkeling_2025/refs/heads/main/Images/Liquid_Logo.png",
        "foundedYear": 2000,
        "manager": "André Kaneyasu",
        "region": "South America"
    }
]